logging4/__init__.py
logging4/logging4.py
logging4-0.0.2.dist-info/METADATA
logging4-0.0.2.dist-info/WHEEL
logging4-0.0.2.dist-info/top_level.txt
logging4-0.0.2.dist-info/RECORD
