Metadata-Version: 2.1
Name: logging4
Version: 0.0.2
Summary: A tiny logging tool
Home-page: https://github.com/guofei9987/logging4
Author: Guo Fei
Author-email: guofei9987@foxmail.com
License: MIT
Platform: linux
Platform: windows
Platform: macos
Requires-Python: >=3.5
